{
  "date": "2023-09-27",
  "games": [
    {
      "game_id": 80076081,
      "home": "NC",
      "home_name": "NC 다이노스",
      "away": "HT",
      "away_name": "KIA 타이거즈",
      "status": "END"
    },
    {
      "game_id": 80076084,
      "home": "SK",
      "home_name": "SSG 랜더스",
      "away": "OB",
      "away_name": "두산 베어스",
      "status": "END"
    },
    {
      "game_id": 80077123,
      "home": "LG",
      "home_name": "LG 트윈스",
      "away": "KT",
      "away_name": "kt wiz",
      "status": "END"
    },
    {
      "game_id": 80077125,
      "home": "HH",
      "home_name": "한화 이글스",
      "away": "SS",
      "away_name": "삼성 라이온즈",
      "status": "END"
    },
    {
      "game_id": 80076082,
      "home": "NC",
      "home_name": "NC 다이노스",
      "away": "HT",
      "away_name": "KIA 타이거즈",
      "status": "END"
    },
    {
      "game_id": 80077124,
      "home": "LG",
      "home_name": "LG 트윈스",
      "away": "KT",
      "away_name": "kt wiz",
      "status": "END"
    },
    {
      "game_id": 80077126,
      "home": "HH",
      "home_name": "한화 이글스",
      "away": "SS",
      "away_name": "삼성 라이온즈",
      "status": "END"
    },
    {
      "game_id": 80076085,
      "home": "SK",
      "home_name": "SSG 랜더스",
      "away": "OB",
      "away_name": "두산 베어스",
      "status": "END"
    }
  ],
  "appearances": [
    {
      "player_id": "69962",
      "name": "송명기",
      "team": "NC 다이노스",
      "team_code": "NC",
      "innings_pitched": "5",
      "pitch_count": 62,
      "is_starter": true,
      "win": 1,
      "loss": 0,
      "save": 0,
      "hold": 0,
      "game_id": 80076081
    },
    {
      "player_id": "65933",
      "name": "구창모",
      "team": "NC 다이노스",
      "team_code": "NC",
      "innings_pitched": "2.1",
      "pitch_count": 44,
      "is_starter": false,
      "win": 0,
      "loss": 0,
      "save": 0,
      "hold": 0,
      "game_id": 80076081
    },
    {
      "player_id": "63959",
      "name": "임정호",
      "team": "NC 다이노스",
      "team_code": "NC",
      "innings_pitched": "0.2",
      "pitch_count": 1,
      "is_starter": false,
      "win": 0,
      "loss": 0,
      "save": 0,
      "hold": 1,
      "game_id": 80076081
    },
    {
      "player_id": "68928",
      "name": "김시훈",
      "team": "NC 다이노스",
      "team_code": "NC",
      "innings_pitched": "1",
      "pitch_count": 14,
      "is_starter": false,
      "win": 0,
      "loss": 0,
      "save": 0,
      "hold": 0,
      "game_id": 80076081
    },
    {
      "player_id": "53665",
      "name": "산체스",
      "team": "KIA 타이거즈",
      "team_code": "HT",
      "innings_pitched": "5",
      "pitch_count": 86,
      "is_starter": true,
      "win": 0,
      "loss": 1,
      "save": 0,
      "hold": 0,
      "game_id": 80076081
    },
    {
      "player_id": "68619",
      "name": "윤중현",
      "team": "KIA 타이거즈",
      "team_code": "HT",
      "innings_pitched": "2",
      "pitch_count": 16,
      "is_starter": false,
      "win": 0,
      "loss": 0,
      "save": 0,
      "hold": 0,
      "game_id": 80076081
    },
    {
      "player_id": "53609",
      "name": "곽도규",
      "team": "KIA 타이거즈",
      "team_code": "HT",
      "innings_pitched": "0.2",
      "pitch_count": 11,
      "is_starter": false,
      "win": 0,
      "loss": 0,
      "save": 0,
      "hold": 0,
      "game_id": 80076081
    },
    {
      "player_id": "66492",
      "name": "김승현",
      "team": "KIA 타이거즈",
      "team_code": "HT",
      "innings_pitched": "0.1",
      "pitch_count": 6,
      "is_starter": false,
      "win": 0,
      "loss": 0,
      "save": 0,
      "hold": 0,
      "game_id": 80076081
    },
    {
      "player_id": "77829",
      "name": "김광현",
      "team": "SSG 랜더스",
      "team_code": "SK",
      "innings_pitched": "6",
      "pitch_count": 95,
      "is_starter": true,
      "win": 0,
      "loss": 0,
      "save": 0,
      "hold": 0,
      "game_id": 80076084
    },
    {
      "player_id": "73211",
      "name": "노경은",
      "team": "SSG 랜더스",
      "team_code": "SK",
      "innings_pitched": "0.2",
      "pitch_count": 19,
      "is_starter": false,
      "win": 0,
      "loss": 0,
      "save": 0,
      "hold": 0,
      "game_id": 80076084
    },
    {
      "player_id": "72523",
      "name": "고효준",
      "team": "SSG 랜더스",
      "team_code": "SK",
      "innings_pitched": "0",
      "pitch_count": 34,
      "is_starter": false,
      "win": 0,
      "loss": 0,
      "save": 0,
      "hold": 0,
      "game_id": 80076084
    },
    {
      "player_id": "64861",
      "name": "이건욱",
      "team": "SSG 랜더스",
      "team_code": "SK",
      "innings_pitched": "0",
      "pitch_count": 9,
      "is_starter": false,
      "win": 0,
      "loss": 0,
      "save": 0,
      "hold": 0,
      "game_id": 80076084
    },
    {
      "player_id": "68856",
      "name": "최민준",
      "team": "SSG 랜더스",
      "team_code": "SK",
      "innings_pitched": "1.1",
      "pitch_count": 15,
      "is_starter": false,
      "win": 0,
      "loss": 0,
      "save": 0,
      "hold": 0,
      "game_id": 80076084
    },
    {
      "player_id": "53892",
      "name": "이로운",
      "team": "SSG 랜더스",
      "team_code": "SK",
      "innings_pitched": "1",
      "pitch_count": 16,
      "is_starter": false,
      "win": 0,
      "loss": 0,
      "save": 0,
      "hold": 0,
      "game_id": 80076084
    },
    {
      "player_id": "52257",
      "name": "브랜든",
      "team": "두산 베어스",
      "team_code": "OB",
      "innings_pitched": "4",
      "pitch_count": 94,
      "is_starter": true,
      "win": 0,
      "loss": 0,
      "save": 0,
      "hold": 0,
      "game_id": 80076084
    },
    {
      "player_id": "68249",
      "name": "박신지",
      "team": "두산 베어스",
      "team_code": "OB",
      "innings_pitched": "2",
      "pitch_count": 26,
      "is_starter": false,
      "win": 0,
      "loss": 0,
      "save": 0,
      "hold": 0,
      "game_id": 80076084
    },
    {
      "player_id": "61643",
      "name": "홍건희",
      "team": "두산 베어스",
      "team_code": "OB",
      "innings_pitched": "1",
      "pitch_count": 22,
      "is_starter": false,
      "win": 0,
      "loss": 0,
      "save": 0,
      "hold": 0,
      "game_id": 80076084
    },
    {
      "player_id": "67246",
      "name": "김명신",
      "team": "두산 베어스",
      "team_code": "OB",
      "innings_pitched": "0.2",
      "pitch_count": 24,
      "is_starter": false,
      "win": 0,
      "loss": 0,
      "save": 0,
      "hold": 0,
      "game_id": 80076084
    },
    {
      "player_id": "68242",
      "name": "정철원",
      "team": "두산 베어스",
      "team_code": "OB",
      "innings_pitched": "1.1",
      "pitch_count": 29,
      "is_starter": false,
      "win": 0,
      "loss": 0,
      "save": 0,
      "hold": 0,
      "game_id": 80076084
    },
    {
      "player_id": "69103",
      "name": "켈리",
      "team": "LG 트윈스",
      "team_code": "LG",
      "innings_pitched": "7",
      "pitch_count": 92,
      "is_starter": true,
      "win": 1,
      "loss": 0,
      "save": 0,
      "hold": 0,
      "game_id": 80077123
    },
    {
      "player_id": "65109",
      "name": "백승현",
      "team": "LG 트윈스",
      "team_code": "LG",
      "innings_pitched": "0.1",
      "pitch_count": 12,
      "is_starter": false,
      "win": 0,
      "loss": 0,
      "save": 0,
      "hold": 1,
      "game_id": 80077123
    },
    {
      "player_id": "75867",
      "name": "김진성",
      "team": "LG 트윈스",
      "team_code": "LG",
      "innings_pitched": "0.2",
      "pitch_count": 9,
      "is_starter": false,
      "win": 0,
      "loss": 0,
      "save": 0,
      "hold": 1,
      "game_id": 80077123
    },
    {
      "player_id": "50106",
      "name": "유영찬",
      "team": "LG 트윈스",
      "team_code": "LG",
      "innings_pitched": "1",
      "pitch_count": 22,
      "is_starter": false,
      "win": 0,
      "loss": 0,
      "save": 0,
      "hold": 0,
      "game_id": 80077123
    },
    {
      "player_id": "65060",
      "name": "주권",
      "team": "kt wiz",
      "team_code": "KT",
      "innings_pitched": "1.1",
      "pitch_count": 40,
      "is_starter": true,
      "win": 0,
      "loss": 0,
      "save": 0,
      "hold": 0,
      "game_id": 80077123
    },
    {
      "player_id": "78517",
      "name": "하준호",
      "team": "kt wiz",
      "team_code": "KT",
      "innings_pitched": "3",
      "pitch_count": 39,
      "is_starter": false,
      "win": 0,
      "loss": 1,
      "save": 0,
      "hold": 0,
      "game_id": 80077123
    },
    {
      "player_id": "68896",
      "name": "이채호",
      "team": "kt wiz",
      "team_code": "KT",
      "innings_pitched": "0",
      "pitch_count": 9,
      "is_starter": false,
      "win": 0,
      "loss": 0,
      "save": 0,
      "hold": 0,
      "game_id": 80077123
    },
    {
      "player_id": "51097",
      "name": "김영현",
      "team": "kt wiz",
      "team_code": "KT",
      "innings_pitched": "2",
      "pitch_count": 31,
      "is_starter": false,
      "win": 0,
      "loss": 0,
      "save": 0,
      "hold": 0,
      "game_id": 80077123
    },
    {
      "player_id": "64768",
      "name": "조이현",
      "team": "kt wiz",
      "team_code": "KT",
      "innings_pitched": "1.2",
      "pitch_count": 20,
      "is_starter": false,
      "win": 0,
      "loss": 0,
      "save": 0,
      "hold": 0,
      "game_id": 80077123
    },
    {
      "player_id": "51715",
      "name": "김기중",
      "team": "한화 이글스",
      "team_code": "HH",
      "innings_pitched": "5",
      "pitch_count": 76,
      "is_starter": true,
      "win": 0,
      "loss": 0,
      "save": 0,
      "hold": 0,
      "game_id": 80077125
    },
    {
      "player_id": "51713",
      "name": "김규연",
      "team": "한화 이글스",
      "team_code": "HH",
      "innings_pitched": "0.2",
      "pitch_count": 23,
      "is_starter": false,
      "win": 0,
      "loss": 0,
      "save": 0,
      "hold": 0,
      "game_id": 80077125
    },
    {
      "player_id": "65769",
      "name": "김범수",
      "team": "한화 이글스",
      "team_code": "HH",
      "innings_pitched": "0.1",
      "pitch_count": 4,
      "is_starter": false,
      "win": 0,
      "loss": 0,
      "save": 0,
      "hold": 0,
      "game_id": 80077125
    },
    {
      "player_id": "63464",
      "name": "윤대경",
      "team": "한화 이글스",
      "team_code": "HH",
      "innings_pitched": "0.2",
      "pitch_count": 15,
      "is_starter": false,
      "win": 0,
      "loss": 0,
      "save": 0,
      "hold": 0,
      "game_id": 80077125
    },
    {
      "player_id": "65707",
      "name": "주현상",
      "team": "한화 이글스",
      "team_code": "HH",
      "innings_pitched": "0.1",
      "pitch_count": 5,
      "is_starter": false,
      "win": 0,
      "loss": 0,
      "save": 0,
      "hold": 0,
      "game_id": 80077125
    },
    {
      "player_id": "77318",
      "name": "장시환",
      "team": "한화 이글스",
      "team_code": "HH",
      "innings_pitched": "0.1",
      "pitch_count": 12,
      "is_starter": false,
      "win": 0,
      "loss": 1,
      "save": 0,
      "hold": 0,
      "game_id": 80077125
    },
    {
      "player_id": "67703",
      "name": "박상원",
      "team": "한화 이글스",
      "team_code": "HH",
      "innings_pitched": "0.1",
      "pitch_count": 22,
      "is_starter": false,
      "win": 0,
      "loss": 0,
      "save": 0,
      "hold": 0,
      "game_id": 80077125
    },
    {
      "player_id": "65616",
      "name": "이민우",
      "team": "한화 이글스",
      "team_code": "HH",
      "innings_pitched": "0.1",
      "pitch_count": 5,
      "is_starter": false,
      "win": 0,
      "loss": 0,
      "save": 0,
      "hold": 0,
      "game_id": 80077125
    },
    {
      "player_id": "52731",
      "name": "박준영",
      "team": "한화 이글스",
      "team_code": "HH",
      "innings_pitched": "0.1",
      "pitch_count": 24,
      "is_starter": false,
      "win": 0,
      "loss": 0,
      "save": 0,
      "hold": 0,
      "game_id": 80077125
    },
    {
      "player_id": "79764",
      "name": "장민재",
      "team": "한화 이글스",
      "team_code": "HH",
      "innings_pitched": "0.2",
      "pitch_count": 15,
      "is_starter": false,
      "win": 0,
      "loss": 0,
      "save": 0,
      "hold": 0,
      "game_id": 80077125
    },
    {
      "player_id": "53927",
      "name": "와이드너",
      "team": "삼성 라이온즈",
      "team_code": "SS",
      "innings_pitched": "6",
      "pitch_count": 98,
      "is_starter": true,
      "win": 0,
      "loss": 0,
      "save": 0,
      "hold": 0,
      "game_id": 80077125
    },
    {
      "player_id": "62360",
      "name": "김태훈",
      "team": "삼성 라이온즈",
      "team_code": "SS",
      "innings_pitched": "0.2",
      "pitch_count": 13,
      "is_starter": false,
      "win": 0,
      "loss": 0,
      "save": 0,
      "hold": 0,
      "game_id": 80077125
    },
    {
      "player_id": "63492",
      "name": "이재익",
      "team": "삼성 라이온즈",
      "team_code": "SS",
      "innings_pitched": "0.1",
      "pitch_count": 4,
      "is_starter": false,
      "win": 1,
      "loss": 0,
      "save": 0,
      "hold": 0,
      "game_id": 80077125
    },
    {
      "player_id": "60146",
      "name": "이승현",
      "team": "삼성 라이온즈",
      "team_code": "SS",
      "innings_pitched": "0.2",
      "pitch_count": 15,
      "is_starter": false,
      "win": 0,
      "loss": 0,
      "save": 0,
      "hold": 1,
      "game_id": 80077125
    },
    {
      "player_id": "75421",
      "name": "오승환",
      "team": "삼성 라이온즈",
      "team_code": "SS",
      "innings_pitched": "1.1",
      "pitch_count": 26,
      "is_starter": false,
      "win": 0,
      "loss": 0,
      "save": 1,
      "hold": 0,
      "game_id": 80077125
    },
    {
      "player_id": "53909",
      "name": "태너",
      "team": "NC 다이노스",
      "team_code": "NC",
      "innings_pitched": "6",
      "pitch_count": 90,
      "is_starter": true,
      "win": 0,
      "loss": 1,
      "save": 0,
      "hold": 0,
      "game_id": 80076082
    },
    {
      "player_id": "51948",
      "name": "이용준",
      "team": "NC 다이노스",
      "team_code": "NC",
      "innings_pitched": "3",
      "pitch_count": 52,
      "is_starter": false,
      "win": 0,
      "loss": 0,
      "save": 0,
      "hold": 0,
      "game_id": 80076082
    },
    {
      "player_id": "51648",
      "name": "이의리",
      "team": "KIA 타이거즈",
      "team_code": "HT",
      "innings_pitched": "7",
      "pitch_count": 77,
      "is_starter": true,
      "win": 1,
      "loss": 0,
      "save": 0,
      "hold": 0,
      "game_id": 80076082
    },
    {
      "player_id": "63950",
      "name": "장현식",
      "team": "KIA 타이거즈",
      "team_code": "HT",
      "innings_pitched": "1",
      "pitch_count": 18,
      "is_starter": false,
      "win": 0,
      "loss": 0,
      "save": 0,
      "hold": 0,
      "game_id": 80076082
    },
    {
      "player_id": "60337",
      "name": "김대유",
      "team": "KIA 타이거즈",
      "team_code": "HT",
      "innings_pitched": "1",
      "pitch_count": 20,
      "is_starter": false,
      "win": 0,
      "loss": 0,
      "save": 0,
      "hold": 0,
      "game_id": 80076082
    },
    {
      "player_id": "50157",
      "name": "김윤식",
      "team": "LG 트윈스",
      "team_code": "LG",
      "innings_pitched": "5",
      "pitch_count": 72,
      "is_starter": true,
      "win": 1,
      "loss": 0,
      "save": 0,
      "hold": 0,
      "game_id": 80077124
    },
    {
      "player_id": "69108",
      "name": "이지강",
      "team": "LG 트윈스",
      "team_code": "LG",
      "innings_pitched": "1",
      "pitch_count": 11,
      "is_starter": false,
      "win": 0,
      "loss": 0,
      "save": 0,
      "hold": 1,
      "game_id": 80077124
    },
    {
      "player_id": "53139",
      "name": "박명근",
      "team": "LG 트윈스",
      "team_code": "LG",
      "innings_pitched": "1.1",
      "pitch_count": 24,
      "is_starter": false,
      "win": 0,
      "loss": 0,
      "save": 0,
      "hold": 1,
      "game_id": 80077124
    },
    {
      "player_id": "75867",
      "name": "김진성",
      "team": "LG 트윈스",
      "team_code": "LG",
      "innings_pitched": "0.2",
      "pitch_count": 9,
      "is_starter": false,
      "win": 0,
      "loss": 0,
      "save": 0,
      "hold": 1,
      "game_id": 80077124
    },
    {
      "player_id": "50106",
      "name": "유영찬",
      "team": "LG 트윈스",
      "team_code": "LG",
      "innings_pitched": "1",
      "pitch_count": 24,
      "is_starter": false,
      "win": 0,
      "loss": 0,
      "save": 1,
      "hold": 0,
      "game_id": 80077124
    },
    {
      "player_id": "65516",
      "name": "배제성",
      "team": "kt wiz",
      "team_code": "KT",
      "innings_pitched": "1.2",
      "pitch_count": 23,
      "is_starter": true,
      "win": 0,
      "loss": 1,
      "save": 0,
      "hold": 0,
      "game_id": 80077124
    },
    {
      "player_id": "69054",
      "name": "이상동",
      "team": "kt wiz",
      "team_code": "KT",
      "innings_pitched": "2.1",
      "pitch_count": 30,
      "is_starter": false,
      "win": 0,
      "loss": 0,
      "save": 0,
      "hold": 0,
      "game_id": 80077124
    },
    {
      "player_id": "69041",
      "name": "손동현",
      "team": "kt wiz",
      "team_code": "KT",
      "innings_pitched": "1",
      "pitch_count": 31,
      "is_starter": false,
      "win": 0,
      "loss": 0,
      "save": 0,
      "hold": 0,
      "game_id": 80077124
    },
    {
      "player_id": "68896",
      "name": "이채호",
      "team": "kt wiz",
      "team_code": "KT",
      "innings_pitched": "2",
      "pitch_count": 34,
      "is_starter": false,
      "win": 0,
      "loss": 0,
      "save": 0,
      "hold": 0,
      "game_id": 80077124
    },
    {
      "player_id": "65062",
      "name": "김재윤",
      "team": "kt wiz",
      "team_code": "KT",
      "innings_pitched": "1",
      "pitch_count": 14,
      "is_starter": false,
      "win": 0,
      "loss": 0,
      "save": 0,
      "hold": 0,
      "game_id": 80077124
    },
    {
      "player_id": "52720",
      "name": "페냐",
      "team": "한화 이글스",
      "team_code": "HH",
      "innings_pitched": "6",
      "pitch_count": 92,
      "is_starter": true,
      "win": 1,
      "loss": 0,
      "save": 0,
      "hold": 0,
      "game_id": 80077126
    },
    {
      "player_id": "65707",
      "name": "주현상",
      "team": "한화 이글스",
      "team_code": "HH",
      "innings_pitched": "1",
      "pitch_count": 9,
      "is_starter": false,
      "win": 0,
      "loss": 0,
      "save": 0,
      "hold": 1,
      "game_id": 80077126
    },
    {
      "player_id": "65769",
      "name": "김범수",
      "team": "한화 이글스",
      "team_code": "HH",
      "innings_pitched": "1",
      "pitch_count": 21,
      "is_starter": false,
      "win": 0,
      "loss": 0,
      "save": 0,
      "hold": 1,
      "game_id": 80077126
    },
    {
      "player_id": "67703",
      "name": "박상원",
      "team": "한화 이글스",
      "team_code": "HH",
      "innings_pitched": "1",
      "pitch_count": 14,
      "is_starter": false,
      "win": 0,
      "loss": 0,
      "save": 0,
      "hold": 0,
      "game_id": 80077126
    },
    {
      "player_id": "50441",
      "name": "황동재",
      "team": "삼성 라이온즈",
      "team_code": "SS",
      "innings_pitched": "4.2",
      "pitch_count": 93,
      "is_starter": true,
      "win": 0,
      "loss": 1,
      "save": 0,
      "hold": 0,
      "game_id": 80077126
    },
    {
      "player_id": "53469",
      "name": "박권후",
      "team": "삼성 라이온즈",
      "team_code": "SS",
      "innings_pitched": "0",
      "pitch_count": 7,
      "is_starter": false,
      "win": 0,
      "loss": 0,
      "save": 0,
      "hold": 0,
      "game_id": 80077126
    },
    {
      "player_id": "65496",
      "name": "홍정우",
      "team": "삼성 라이온즈",
      "team_code": "SS",
      "innings_pitched": "1.1",
      "pitch_count": 11,
      "is_starter": false,
      "win": 0,
      "loss": 0,
      "save": 0,
      "hold": 0,
      "game_id": 80077126
    },
    {
      "player_id": "63492",
      "name": "이재익",
      "team": "삼성 라이온즈",
      "team_code": "SS",
      "innings_pitched": "0.1",
      "pitch_count": 11,
      "is_starter": false,
      "win": 0,
      "loss": 0,
      "save": 0,
      "hold": 0,
      "game_id": 80077126
    },
    {
      "player_id": "67421",
      "name": "최지광",
      "team": "삼성 라이온즈",
      "team_code": "SS",
      "innings_pitched": "0.2",
      "pitch_count": 9,
      "is_starter": false,
      "win": 0,
      "loss": 0,
      "save": 0,
      "hold": 0,
      "game_id": 80077126
    },
    {
      "player_id": "50430",
      "name": "홍원표",
      "team": "삼성 라이온즈",
      "team_code": "SS",
      "innings_pitched": "0.2",
      "pitch_count": 13,
      "is_starter": false,
      "win": 0,
      "loss": 0,
      "save": 0,
      "hold": 0,
      "game_id": 80077126
    },
    {
      "player_id": "61365",
      "name": "김대우",
      "team": "삼성 라이온즈",
      "team_code": "SS",
      "innings_pitched": "0.1",
      "pitch_count": 7,
      "is_starter": false,
      "win": 0,
      "loss": 0,
      "save": 0,
      "hold": 0,
      "game_id": 80077126
    },
    {
      "player_id": "53825",
      "name": "엘리아스",
      "team": "SSG 랜더스",
      "team_code": "SK",
      "innings_pitched": "8",
      "pitch_count": 106,
      "is_starter": true,
      "win": 1,
      "loss": 0,
      "save": 0,
      "hold": 0,
      "game_id": 80076085
    },
    {
      "player_id": "61895",
      "name": "서진용",
      "team": "SSG 랜더스",
      "team_code": "SK",
      "innings_pitched": "1",
      "pitch_count": 17,
      "is_starter": false,
      "win": 0,
      "loss": 0,
      "save": 1,
      "hold": 0,
      "game_id": 80076085
    },
    {
      "player_id": "51264",
      "name": "최승용",
      "team": "두산 베어스",
      "team_code": "OB",
      "innings_pitched": "5",
      "pitch_count": 85,
      "is_starter": true,
      "win": 0,
      "loss": 0,
      "save": 0,
      "hold": 0,
      "game_id": 80076085
    },
    {
      "player_id": "66291",
      "name": "이영하",
      "team": "두산 베어스",
      "team_code": "OB",
      "innings_pitched": "0.1",
      "pitch_count": 29,
      "is_starter": false,
      "win": 0,
      "loss": 1,
      "save": 0,
      "hold": 0,
      "game_id": 80076085
    },
    {
      "player_id": "52206",
      "name": "최지강",
      "team": "두산 베어스",
      "team_code": "OB",
      "innings_pitched": "1",
      "pitch_count": 16,
      "is_starter": false,
      "win": 0,
      "loss": 0,
      "save": 0,
      "hold": 0,
      "game_id": 80076085
    },
    {
      "player_id": "65639",
      "name": "박정수",
      "team": "두산 베어스",
      "team_code": "OB",
      "innings_pitched": "1.2",
      "pitch_count": 23,
      "is_starter": false,
      "win": 0,
      "loss": 0,
      "save": 0,
      "hold": 0,
      "game_id": 80076085
    }
  ]
}