{
  "date": "2023-11-11",
  "games": [
    {
      "game_id": 80078480,
      "home": "KT",
      "home_name": "kt wiz",
      "away": "LG",
      "away_name": "LG 트윈스",
      "status": "END"
    }
  ],
  "appearances": [
    {
      "player_id": "65056",
      "name": "엄상백",
      "team": "kt wiz",
      "team_code": "KT",
      "innings_pitched": "4",
      "pitch_count": 69,
      "is_starter": true,
      "win": 0,
      "loss": 1,
      "save": 0,
      "hold": 0,
      "game_id": 80078480
    },
    {
      "player_id": "65062",
      "name": "김재윤",
      "team": "kt wiz",
      "team_code": "KT",
      "innings_pitched": "1.1",
      "pitch_count": 19,
      "is_starter": false,
      "win": 0,
      "loss": 0,
      "save": 0,
      "hold": 0,
      "game_id": 80078480
    },
    {
      "player_id": "51097",
      "name": "김영현",
      "team": "kt wiz",
      "team_code": "KT",
      "innings_pitched": "1",
      "pitch_count": 16,
      "is_starter": false,
      "win": 0,
      "loss": 0,
      "save": 0,
      "hold": 0,
      "game_id": 80078480
    },
    {
      "player_id": "68043",
      "name": "김민",
      "team": "kt wiz",
      "team_code": "KT",
      "innings_pitched": "0",
      "pitch_count": 7,
      "is_starter": false,
      "win": 0,
      "loss": 0,
      "save": 0,
      "hold": 0,
      "game_id": 80078480
    },
    {
      "player_id": "65060",
      "name": "주권",
      "team": "kt wiz",
      "team_code": "KT",
      "innings_pitched": "0.2",
      "pitch_count": 26,
      "is_starter": false,
      "win": 0,
      "loss": 0,
      "save": 0,
      "hold": 0,
      "game_id": 80078480
    },
    {
      "player_id": "65516",
      "name": "배제성",
      "team": "kt wiz",
      "team_code": "KT",
      "innings_pitched": "2",
      "pitch_count": 59,
      "is_starter": false,
      "win": 0,
      "loss": 0,
      "save": 0,
      "hold": 0,
      "game_id": 80078480
    },
    {
      "player_id": "50157",
      "name": "김윤식",
      "team": "LG 트윈스",
      "team_code": "LG",
      "innings_pitched": "5.2",
      "pitch_count": 87,
      "is_starter": true,
      "win": 1,
      "loss": 0,
      "save": 0,
      "hold": 0,
      "game_id": 80078480
    },
    {
      "player_id": "65109",
      "name": "백승현",
      "team": "LG 트윈스",
      "team_code": "LG",
      "innings_pitched": "0.1",
      "pitch_count": 10,
      "is_starter": false,
      "win": 0,
      "loss": 0,
      "save": 0,
      "hold": 0,
      "game_id": 80078480
    },
    {
      "player_id": "69134",
      "name": "이정용",
      "team": "LG 트윈스",
      "team_code": "LG",
      "innings_pitched": "1",
      "pitch_count": 20,
      "is_starter": false,
      "win": 0,
      "loss": 0,
      "save": 0,
      "hold": 0,
      "game_id": 80078480
    },
    {
      "player_id": "61145",
      "name": "이우찬",
      "team": "LG 트윈스",
      "team_code": "LG",
      "innings_pitched": "0.1",
      "pitch_count": 18,
      "is_starter": false,
      "win": 0,
      "loss": 0,
      "save": 0,
      "hold": 0,
      "game_id": 80078480
    },
    {
      "player_id": "79140",
      "name": "최동환",
      "team": "LG 트윈스",
      "team_code": "LG",
      "innings_pitched": "0.2",
      "pitch_count": 12,
      "is_starter": false,
      "win": 0,
      "loss": 0,
      "save": 0,
      "hold": 0,
      "game_id": 80078480
    },
    {
      "player_id": "65320",
      "name": "최원태",
      "team": "LG 트윈스",
      "team_code": "LG",
      "innings_pitched": "1",
      "pitch_count": 26,
      "is_starter": false,
      "win": 0,
      "loss": 0,
      "save": 0,
      "hold": 0,
      "game_id": 80078480
    }
  ]
}