{
  "date": "2025-08-08",
  "games": [
    {
      "game_id": 80090918,
      "home": "LG",
      "home_name": "LG 트윈스",
      "away": "HH",
      "away_name": "한화 이글스",
      "status": "END"
    },
    {
      "game_id": 80090920,
      "home": "WO",
      "home_name": "키움 히어로즈",
      "away": "OB",
      "away_name": "두산 베어스",
      "status": "END"
    },
    {
      "game_id": 80090921,
      "home": "LT",
      "home_name": "롯데 자이언츠",
      "away": "SK",
      "away_name": "SSG 랜더스",
      "status": "END"
    },
    {
      "game_id": 80090922,
      "home": "KT",
      "home_name": "kt wiz",
      "away": "SS",
      "away_name": "삼성 라이온즈",
      "status": "END"
    },
    {
      "game_id": 80095084,
      "home": "NC",
      "home_name": "NC 다이노스",
      "away": "HT",
      "away_name": "KIA 타이거즈",
      "status": "END"
    }
  ],
  "appearances": [
    {
      "player_id": "61101",
      "name": "임찬규",
      "team": "LG 트윈스",
      "team_code": "LG",
      "innings_pitched": "7",
      "pitch_count": 103,
      "is_starter": true,
      "win": 0,
      "loss": 0,
      "save": 0,
      "hold": 0,
      "game_id": 80090918
    },
    {
      "player_id": "63950",
      "name": "장현식",
      "team": "LG 트윈스",
      "team_code": "LG",
      "innings_pitched": "1",
      "pitch_count": 17,
      "is_starter": false,
      "win": 0,
      "loss": 0,
      "save": 0,
      "hold": 0,
      "game_id": 80090918
    },
    {
      "player_id": "50106",
      "name": "유영찬",
      "team": "LG 트윈스",
      "team_code": "LG",
      "innings_pitched": "1",
      "pitch_count": 17,
      "is_starter": false,
      "win": 0,
      "loss": 0,
      "save": 0,
      "hold": 0,
      "game_id": 80090918
    },
    {
      "player_id": "63248",
      "name": "함덕주",
      "team": "LG 트윈스",
      "team_code": "LG",
      "innings_pitched": "1",
      "pitch_count": 12,
      "is_starter": false,
      "win": 1,
      "loss": 0,
      "save": 0,
      "hold": 0,
      "game_id": 80090918
    },
    {
      "player_id": "76715",
      "name": "류현진",
      "team": "한화 이글스",
      "team_code": "HH",
      "innings_pitched": "6",
      "pitch_count": 88,
      "is_starter": true,
      "win": 0,
      "loss": 0,
      "save": 0,
      "hold": 0,
      "game_id": 80090918
    },
    {
      "player_id": "65707",
      "name": "주현상",
      "team": "한화 이글스",
      "team_code": "HH",
      "innings_pitched": "0.2",
      "pitch_count": 13,
      "is_starter": false,
      "win": 0,
      "loss": 0,
      "save": 0,
      "hold": 0,
      "game_id": 80090918
    },
    {
      "player_id": "65769",
      "name": "김범수",
      "team": "한화 이글스",
      "team_code": "HH",
      "innings_pitched": "1",
      "pitch_count": 13,
      "is_starter": false,
      "win": 0,
      "loss": 0,
      "save": 0,
      "hold": 0,
      "game_id": 80090918
    },
    {
      "player_id": "55743",
      "name": "정우주",
      "team": "한화 이글스",
      "team_code": "HH",
      "innings_pitched": "1",
      "pitch_count": 15,
      "is_starter": false,
      "win": 0,
      "loss": 0,
      "save": 0,
      "hold": 0,
      "game_id": 80090918
    },
    {
      "player_id": "53754",
      "name": "김서현",
      "team": "한화 이글스",
      "team_code": "HH",
      "innings_pitched": "0.2",
      "pitch_count": 32,
      "is_starter": false,
      "win": 0,
      "loss": 1,
      "save": 0,
      "hold": 0,
      "game_id": 80090918
    },
    {
      "player_id": "54319",
      "name": "김윤하",
      "team": "키움 히어로즈",
      "team_code": "WO",
      "innings_pitched": "5",
      "pitch_count": 97,
      "is_starter": true,
      "win": 0,
      "loss": 1,
      "save": 0,
      "hold": 0,
      "game_id": 80090920
    },
    {
      "player_id": "66018",
      "name": "김선기",
      "team": "키움 히어로즈",
      "team_code": "WO",
      "innings_pitched": "2",
      "pitch_count": 28,
      "is_starter": false,
      "win": 0,
      "loss": 0,
      "save": 0,
      "hold": 0,
      "game_id": 80090920
    },
    {
      "player_id": "55394",
      "name": "박정훈",
      "team": "키움 히어로즈",
      "team_code": "WO",
      "innings_pitched": "2",
      "pitch_count": 44,
      "is_starter": false,
      "win": 0,
      "loss": 0,
      "save": 0,
      "hold": 0,
      "game_id": 80090920
    },
    {
      "player_id": "55239",
      "name": "잭로그",
      "team": "두산 베어스",
      "team_code": "OB",
      "innings_pitched": "7",
      "pitch_count": 100,
      "is_starter": true,
      "win": 1,
      "loss": 0,
      "save": 0,
      "hold": 0,
      "game_id": 80090920
    },
    {
      "player_id": "50211",
      "name": "제환유",
      "team": "두산 베어스",
      "team_code": "OB",
      "innings_pitched": "1",
      "pitch_count": 17,
      "is_starter": false,
      "win": 0,
      "loss": 0,
      "save": 0,
      "hold": 0,
      "game_id": 80090920
    },
    {
      "player_id": "69205",
      "name": "이교훈",
      "team": "두산 베어스",
      "team_code": "OB",
      "innings_pitched": "1",
      "pitch_count": 12,
      "is_starter": false,
      "win": 0,
      "loss": 0,
      "save": 0,
      "hold": 0,
      "game_id": 80090920
    },
    {
      "player_id": "67539",
      "name": "나균안",
      "team": "롯데 자이언츠",
      "team_code": "LT",
      "innings_pitched": "6",
      "pitch_count": 99,
      "is_starter": true,
      "win": 0,
      "loss": 1,
      "save": 0,
      "hold": 0,
      "game_id": 80090921
    },
    {
      "player_id": "68242",
      "name": "정철원",
      "team": "롯데 자이언츠",
      "team_code": "LT",
      "innings_pitched": "1",
      "pitch_count": 16,
      "is_starter": false,
      "win": 0,
      "loss": 0,
      "save": 0,
      "hold": 0,
      "game_id": 80090921
    },
    {
      "player_id": "67588",
      "name": "윤성빈",
      "team": "롯데 자이언츠",
      "team_code": "LT",
      "innings_pitched": "1",
      "pitch_count": 12,
      "is_starter": false,
      "win": 0,
      "loss": 0,
      "save": 0,
      "hold": 0,
      "game_id": 80090921
    },
    {
      "player_id": "69594",
      "name": "박진",
      "team": "롯데 자이언츠",
      "team_code": "LT",
      "innings_pitched": "1",
      "pitch_count": 13,
      "is_starter": false,
      "win": 0,
      "loss": 0,
      "save": 0,
      "hold": 0,
      "game_id": 80090921
    },
    {
      "player_id": "68856",
      "name": "최민준",
      "team": "SSG 랜더스",
      "team_code": "SK",
      "innings_pitched": "4.1",
      "pitch_count": 63,
      "is_starter": true,
      "win": 0,
      "loss": 0,
      "save": 0,
      "hold": 0,
      "game_id": 80090921
    },
    {
      "player_id": "50812",
      "name": "박시후",
      "team": "SSG 랜더스",
      "team_code": "SK",
      "innings_pitched": "0.1",
      "pitch_count": 9,
      "is_starter": false,
      "win": 0,
      "loss": 0,
      "save": 0,
      "hold": 1,
      "game_id": 80090921
    },
    {
      "player_id": "68043",
      "name": "김민",
      "team": "SSG 랜더스",
      "team_code": "SK",
      "innings_pitched": "1.1",
      "pitch_count": 12,
      "is_starter": false,
      "win": 1,
      "loss": 0,
      "save": 0,
      "hold": 0,
      "game_id": 80090921
    },
    {
      "player_id": "53892",
      "name": "이로운",
      "team": "SSG 랜더스",
      "team_code": "SK",
      "innings_pitched": "1",
      "pitch_count": 11,
      "is_starter": false,
      "win": 0,
      "loss": 0,
      "save": 0,
      "hold": 1,
      "game_id": 80090921
    },
    {
      "player_id": "73211",
      "name": "노경은",
      "team": "SSG 랜더스",
      "team_code": "SK",
      "innings_pitched": "1",
      "pitch_count": 22,
      "is_starter": false,
      "win": 0,
      "loss": 0,
      "save": 0,
      "hold": 1,
      "game_id": 80090921
    },
    {
      "player_id": "51897",
      "name": "조병현",
      "team": "SSG 랜더스",
      "team_code": "SK",
      "innings_pitched": "1",
      "pitch_count": 15,
      "is_starter": false,
      "win": 0,
      "loss": 0,
      "save": 1,
      "hold": 0,
      "game_id": 80090921
    },
    {
      "player_id": "50030",
      "name": "소형준",
      "team": "kt wiz",
      "team_code": "KT",
      "innings_pitched": "6",
      "pitch_count": 96,
      "is_starter": true,
      "win": 0,
      "loss": 1,
      "save": 0,
      "hold": 0,
      "game_id": 80090922
    },
    {
      "player_id": "65060",
      "name": "주권",
      "team": "kt wiz",
      "team_code": "KT",
      "innings_pitched": "2",
      "pitch_count": 34,
      "is_starter": false,
      "win": 0,
      "loss": 0,
      "save": 0,
      "hold": 0,
      "game_id": 80090922
    },
    {
      "player_id": "69047",
      "name": "전용주",
      "team": "kt wiz",
      "team_code": "KT",
      "innings_pitched": "0.1",
      "pitch_count": 11,
      "is_starter": false,
      "win": 0,
      "loss": 0,
      "save": 0,
      "hold": 0,
      "game_id": 80090922
    },
    {
      "player_id": "69054",
      "name": "이상동",
      "team": "kt wiz",
      "team_code": "KT",
      "innings_pitched": "0",
      "pitch_count": 2,
      "is_starter": false,
      "win": 0,
      "loss": 0,
      "save": 0,
      "hold": 0,
      "game_id": 80090922
    },
    {
      "player_id": "67048",
      "name": "이정현",
      "team": "kt wiz",
      "team_code": "KT",
      "innings_pitched": "0.2",
      "pitch_count": 8,
      "is_starter": false,
      "win": 0,
      "loss": 0,
      "save": 0,
      "hold": 0,
      "game_id": 80090922
    },
    {
      "player_id": "69446",
      "name": "원태인",
      "team": "삼성 라이온즈",
      "team_code": "SS",
      "innings_pitched": "7.1",
      "pitch_count": 102,
      "is_starter": true,
      "win": 1,
      "loss": 0,
      "save": 0,
      "hold": 0,
      "game_id": 80090922
    },
    {
      "player_id": "55455",
      "name": "배찬승",
      "team": "삼성 라이온즈",
      "team_code": "SS",
      "innings_pitched": "0.2",
      "pitch_count": 11,
      "is_starter": false,
      "win": 0,
      "loss": 0,
      "save": 0,
      "hold": 1,
      "game_id": 80090922
    },
    {
      "player_id": "65062",
      "name": "김재윤",
      "team": "삼성 라이온즈",
      "team_code": "SS",
      "innings_pitched": "1",
      "pitch_count": 8,
      "is_starter": false,
      "win": 0,
      "loss": 0,
      "save": 0,
      "hold": 0,
      "game_id": 80090922
    },
    {
      "player_id": "55903",
      "name": "라일리",
      "team": "NC 다이노스",
      "team_code": "NC",
      "innings_pitched": "6",
      "pitch_count": 115,
      "is_starter": true,
      "win": 1,
      "loss": 0,
      "save": 0,
      "hold": 0,
      "game_id": 80095084
    },
    {
      "player_id": "64995",
      "name": "배재환",
      "team": "NC 다이노스",
      "team_code": "NC",
      "innings_pitched": "1",
      "pitch_count": 16,
      "is_starter": false,
      "win": 0,
      "loss": 0,
      "save": 0,
      "hold": 1,
      "game_id": 80095084
    },
    {
      "player_id": "68900",
      "name": "김영규",
      "team": "NC 다이노스",
      "team_code": "NC",
      "innings_pitched": "0.2",
      "pitch_count": 28,
      "is_starter": false,
      "win": 0,
      "loss": 0,
      "save": 0,
      "hold": 1,
      "game_id": 80095084
    },
    {
      "player_id": "65949",
      "name": "류진욱",
      "team": "NC 다이노스",
      "team_code": "NC",
      "innings_pitched": "1.1",
      "pitch_count": 11,
      "is_starter": false,
      "win": 0,
      "loss": 0,
      "save": 1,
      "hold": 0,
      "game_id": 80095084
    },
    {
      "player_id": "69745",
      "name": "김도현",
      "team": "KIA 타이거즈",
      "team_code": "HT",
      "innings_pitched": "6",
      "pitch_count": 79,
      "is_starter": true,
      "win": 0,
      "loss": 1,
      "save": 0,
      "hold": 0,
      "game_id": 80095084
    },
    {
      "player_id": "69620",
      "name": "김기훈",
      "team": "KIA 타이거즈",
      "team_code": "HT",
      "innings_pitched": "1",
      "pitch_count": 22,
      "is_starter": false,
      "win": 0,
      "loss": 0,
      "save": 0,
      "hold": 0,
      "game_id": 80095084
    },
    {
      "player_id": "52639",
      "name": "최지민",
      "team": "KIA 타이거즈",
      "team_code": "HT",
      "innings_pitched": "1",
      "pitch_count": 5,
      "is_starter": false,
      "win": 0,
      "loss": 0,
      "save": 0,
      "hold": 0,
      "game_id": 80095084
    }
  ]
}