{
  "date": "2022-05-17",
  "games": [
    {
      "game_id": 80055220,
      "home": "LT",
      "home_name": "롯데 자이언츠",
      "away": "HT",
      "away_name": "KIA 타이거즈",
      "status": "END"
    },
    {
      "game_id": 80055221,
      "home": "KT",
      "home_name": "kt wiz",
      "away": "LG",
      "away_name": "LG 트윈스",
      "status": "END"
    },
    {
      "game_id": 80055222,
      "home": "OB",
      "home_name": "두산 베어스",
      "away": "SK",
      "away_name": "SSG 랜더스",
      "status": "END"
    },
    {
      "game_id": 80055223,
      "home": "HH",
      "home_name": "한화 이글스",
      "away": "SS",
      "away_name": "삼성 라이온즈",
      "status": "END"
    },
    {
      "game_id": 80055224,
      "home": "NC",
      "home_name": "NC 다이노스",
      "away": "WO",
      "away_name": "키움 히어로즈",
      "status": "END"
    }
  ],
  "appearances": [
    {
      "player_id": "52557",
      "name": "스파크맨",
      "team": "롯데 자이언츠",
      "team_code": "LT",
      "innings_pitched": "6",
      "pitch_count": 90,
      "is_starter": true,
      "win": 0,
      "loss": 0,
      "save": 0,
      "hold": 0,
      "game_id": 80055220
    },
    {
      "player_id": "64596",
      "name": "김유영",
      "team": "롯데 자이언츠",
      "team_code": "LT",
      "innings_pitched": "0",
      "pitch_count": 8,
      "is_starter": false,
      "win": 0,
      "loss": 0,
      "save": 0,
      "hold": 0,
      "game_id": 80055220
    },
    {
      "player_id": "62528",
      "name": "김원중",
      "team": "롯데 자이언츠",
      "team_code": "LT",
      "innings_pitched": "1",
      "pitch_count": 14,
      "is_starter": false,
      "win": 0,
      "loss": 0,
      "save": 0,
      "hold": 0,
      "game_id": 80055220
    },
    {
      "player_id": "63543",
      "name": "구승민",
      "team": "롯데 자이언츠",
      "team_code": "LT",
      "innings_pitched": "1",
      "pitch_count": 21,
      "is_starter": false,
      "win": 0,
      "loss": 0,
      "save": 0,
      "hold": 0,
      "game_id": 80055220
    },
    {
      "player_id": "50556",
      "name": "최준용",
      "team": "롯데 자이언츠",
      "team_code": "LT",
      "innings_pitched": "1",
      "pitch_count": 28,
      "is_starter": false,
      "win": 0,
      "loss": 1,
      "save": 0,
      "hold": 0,
      "game_id": 80055220
    },
    {
      "player_id": "51648",
      "name": "이의리",
      "team": "KIA 타이거즈",
      "team_code": "HT",
      "innings_pitched": "7",
      "pitch_count": 92,
      "is_starter": true,
      "win": 0,
      "loss": 0,
      "save": 0,
      "hold": 0,
      "game_id": 80055220
    },
    {
      "player_id": "63950",
      "name": "장현식",
      "team": "KIA 타이거즈",
      "team_code": "HT",
      "innings_pitched": "1",
      "pitch_count": 23,
      "is_starter": false,
      "win": 1,
      "loss": 0,
      "save": 0,
      "hold": 0,
      "game_id": 80055220
    },
    {
      "player_id": "50662",
      "name": "정해영",
      "team": "KIA 타이거즈",
      "team_code": "HT",
      "innings_pitched": "1",
      "pitch_count": 8,
      "is_starter": false,
      "win": 0,
      "loss": 0,
      "save": 1,
      "hold": 0,
      "game_id": 80055220
    },
    {
      "player_id": "50040",
      "name": "데스파이네",
      "team": "kt wiz",
      "team_code": "KT",
      "innings_pitched": "7",
      "pitch_count": 102,
      "is_starter": true,
      "win": 0,
      "loss": 0,
      "save": 0,
      "hold": 0,
      "game_id": 80055221
    },
    {
      "player_id": "64017",
      "name": "심재민",
      "team": "kt wiz",
      "team_code": "KT",
      "innings_pitched": "1",
      "pitch_count": 17,
      "is_starter": false,
      "win": 0,
      "loss": 0,
      "save": 0,
      "hold": 0,
      "game_id": 80055221
    },
    {
      "player_id": "65062",
      "name": "김재윤",
      "team": "kt wiz",
      "team_code": "KT",
      "innings_pitched": "1",
      "pitch_count": 10,
      "is_starter": false,
      "win": 1,
      "loss": 0,
      "save": 0,
      "hold": 0,
      "game_id": 80055221
    },
    {
      "player_id": "69103",
      "name": "켈리",
      "team": "LG 트윈스",
      "team_code": "LG",
      "innings_pitched": "6",
      "pitch_count": 93,
      "is_starter": true,
      "win": 0,
      "loss": 0,
      "save": 0,
      "hold": 0,
      "game_id": 80055221
    },
    {
      "player_id": "69134",
      "name": "이정용",
      "team": "LG 트윈스",
      "team_code": "LG",
      "innings_pitched": "1",
      "pitch_count": 14,
      "is_starter": false,
      "win": 0,
      "loss": 0,
      "save": 0,
      "hold": 1,
      "game_id": 80055221
    },
    {
      "player_id": "60337",
      "name": "김대유",
      "team": "LG 트윈스",
      "team_code": "LG",
      "innings_pitched": "0.1",
      "pitch_count": 10,
      "is_starter": false,
      "win": 0,
      "loss": 0,
      "save": 0,
      "hold": 1,
      "game_id": 80055221
    },
    {
      "player_id": "69159",
      "name": "정우영",
      "team": "LG 트윈스",
      "team_code": "LG",
      "innings_pitched": "0.2",
      "pitch_count": 21,
      "is_starter": false,
      "win": 0,
      "loss": 0,
      "save": 0,
      "hold": 0,
      "game_id": 80055221
    },
    {
      "player_id": "75867",
      "name": "김진성",
      "team": "LG 트윈스",
      "team_code": "LG",
      "innings_pitched": "0.1",
      "pitch_count": 8,
      "is_starter": false,
      "win": 0,
      "loss": 1,
      "save": 0,
      "hold": 0,
      "game_id": 80055221
    },
    {
      "player_id": "66291",
      "name": "이영하",
      "team": "두산 베어스",
      "team_code": "OB",
      "innings_pitched": "1.2",
      "pitch_count": 60,
      "is_starter": true,
      "win": 0,
      "loss": 0,
      "save": 0,
      "hold": 0,
      "game_id": 80055222
    },
    {
      "player_id": "68249",
      "name": "박신지",
      "team": "두산 베어스",
      "team_code": "OB",
      "innings_pitched": "1",
      "pitch_count": 22,
      "is_starter": false,
      "win": 0,
      "loss": 0,
      "save": 0,
      "hold": 0,
      "game_id": 80055222
    },
    {
      "player_id": "65639",
      "name": "박정수",
      "team": "두산 베어스",
      "team_code": "OB",
      "innings_pitched": "3.1",
      "pitch_count": 46,
      "is_starter": false,
      "win": 0,
      "loss": 0,
      "save": 0,
      "hold": 0,
      "game_id": 80055222
    },
    {
      "player_id": "67246",
      "name": "김명신",
      "team": "두산 베어스",
      "team_code": "OB",
      "innings_pitched": "1",
      "pitch_count": 23,
      "is_starter": false,
      "win": 0,
      "loss": 0,
      "save": 0,
      "hold": 0,
      "game_id": 80055222
    },
    {
      "player_id": "50203",
      "name": "권휘",
      "team": "두산 베어스",
      "team_code": "OB",
      "innings_pitched": "1",
      "pitch_count": 13,
      "is_starter": false,
      "win": 0,
      "loss": 0,
      "save": 0,
      "hold": 0,
      "game_id": 80055222
    },
    {
      "player_id": "68242",
      "name": "정철원",
      "team": "두산 베어스",
      "team_code": "OB",
      "innings_pitched": "2",
      "pitch_count": 34,
      "is_starter": false,
      "win": 0,
      "loss": 0,
      "save": 0,
      "hold": 0,
      "game_id": 80055222
    },
    {
      "player_id": "61643",
      "name": "홍건희",
      "team": "두산 베어스",
      "team_code": "OB",
      "innings_pitched": "2",
      "pitch_count": 23,
      "is_starter": false,
      "win": 0,
      "loss": 0,
      "save": 0,
      "hold": 0,
      "game_id": 80055222
    },
    {
      "player_id": "52833",
      "name": "노바",
      "team": "SSG 랜더스",
      "team_code": "SK",
      "innings_pitched": "5.1",
      "pitch_count": 94,
      "is_starter": true,
      "win": 0,
      "loss": 0,
      "save": 0,
      "hold": 0,
      "game_id": 80055222
    },
    {
      "player_id": "72523",
      "name": "고효준",
      "team": "SSG 랜더스",
      "team_code": "SK",
      "innings_pitched": "0.2",
      "pitch_count": 18,
      "is_starter": false,
      "win": 0,
      "loss": 0,
      "save": 0,
      "hold": 0,
      "game_id": 80055222
    },
    {
      "player_id": "51809",
      "name": "조요한",
      "team": "SSG 랜더스",
      "team_code": "SK",
      "innings_pitched": "1",
      "pitch_count": 10,
      "is_starter": false,
      "win": 0,
      "loss": 0,
      "save": 0,
      "hold": 0,
      "game_id": 80055222
    },
    {
      "player_id": "68092",
      "name": "한두솔",
      "team": "SSG 랜더스",
      "team_code": "SK",
      "innings_pitched": "0",
      "pitch_count": 8,
      "is_starter": false,
      "win": 0,
      "loss": 0,
      "save": 0,
      "hold": 0,
      "game_id": 80055222
    },
    {
      "player_id": "52867",
      "name": "윤태현",
      "team": "SSG 랜더스",
      "team_code": "SK",
      "innings_pitched": "0",
      "pitch_count": 12,
      "is_starter": false,
      "win": 0,
      "loss": 0,
      "save": 0,
      "hold": 0,
      "game_id": 80055222
    },
    {
      "player_id": "79847",
      "name": "김태훈",
      "team": "SSG 랜더스",
      "team_code": "SK",
      "innings_pitched": "0.1",
      "pitch_count": 18,
      "is_starter": false,
      "win": 0,
      "loss": 0,
      "save": 0,
      "hold": 1,
      "game_id": 80055222
    },
    {
      "player_id": "61895",
      "name": "서진용",
      "team": "SSG 랜더스",
      "team_code": "SK",
      "innings_pitched": "1.2",
      "pitch_count": 19,
      "is_starter": false,
      "win": 0,
      "loss": 0,
      "save": 0,
      "hold": 0,
      "game_id": 80055222
    },
    {
      "player_id": "68856",
      "name": "최민준",
      "team": "SSG 랜더스",
      "team_code": "SK",
      "innings_pitched": "3",
      "pitch_count": 39,
      "is_starter": false,
      "win": 0,
      "loss": 0,
      "save": 0,
      "hold": 0,
      "game_id": 80055222
    },
    {
      "player_id": "65616",
      "name": "이민우",
      "team": "한화 이글스",
      "team_code": "HH",
      "innings_pitched": "5",
      "pitch_count": 72,
      "is_starter": true,
      "win": 1,
      "loss": 0,
      "save": 0,
      "hold": 0,
      "game_id": 80055223
    },
    {
      "player_id": "50705",
      "name": "강재민",
      "team": "한화 이글스",
      "team_code": "HH",
      "innings_pitched": "0.2",
      "pitch_count": 6,
      "is_starter": false,
      "win": 0,
      "loss": 0,
      "save": 0,
      "hold": 1,
      "game_id": 80055223
    },
    {
      "player_id": "65769",
      "name": "김범수",
      "team": "한화 이글스",
      "team_code": "HH",
      "innings_pitched": "0.1",
      "pitch_count": 9,
      "is_starter": false,
      "win": 0,
      "loss": 0,
      "save": 0,
      "hold": 1,
      "game_id": 80055223
    },
    {
      "player_id": "63765",
      "name": "김종수",
      "team": "한화 이글스",
      "team_code": "HH",
      "innings_pitched": "1",
      "pitch_count": 8,
      "is_starter": false,
      "win": 0,
      "loss": 0,
      "save": 0,
      "hold": 1,
      "game_id": 80055223
    },
    {
      "player_id": "65707",
      "name": "주현상",
      "team": "한화 이글스",
      "team_code": "HH",
      "innings_pitched": "1",
      "pitch_count": 10,
      "is_starter": false,
      "win": 0,
      "loss": 0,
      "save": 0,
      "hold": 1,
      "game_id": 80055223
    },
    {
      "player_id": "77318",
      "name": "장시환",
      "team": "한화 이글스",
      "team_code": "HH",
      "innings_pitched": "1",
      "pitch_count": 26,
      "is_starter": false,
      "win": 0,
      "loss": 0,
      "save": 1,
      "hold": 0,
      "game_id": 80055223
    },
    {
      "player_id": "77446",
      "name": "백정현",
      "team": "삼성 라이온즈",
      "team_code": "SS",
      "innings_pitched": "6",
      "pitch_count": 95,
      "is_starter": true,
      "win": 0,
      "loss": 1,
      "save": 0,
      "hold": 0,
      "game_id": 80055223
    },
    {
      "player_id": "63492",
      "name": "이재익",
      "team": "삼성 라이온즈",
      "team_code": "SS",
      "innings_pitched": "0.2",
      "pitch_count": 20,
      "is_starter": false,
      "win": 0,
      "loss": 0,
      "save": 0,
      "hold": 0,
      "game_id": 80055223
    },
    {
      "player_id": "66493",
      "name": "임대한",
      "team": "삼성 라이온즈",
      "team_code": "SS",
      "innings_pitched": "0.1",
      "pitch_count": 8,
      "is_starter": false,
      "win": 0,
      "loss": 0,
      "save": 0,
      "hold": 0,
      "game_id": 80055223
    },
    {
      "player_id": "60146",
      "name": "이승현",
      "team": "삼성 라이온즈",
      "team_code": "SS",
      "innings_pitched": "1",
      "pitch_count": 11,
      "is_starter": false,
      "win": 0,
      "loss": 0,
      "save": 0,
      "hold": 0,
      "game_id": 80055223
    },
    {
      "player_id": "69962",
      "name": "송명기",
      "team": "NC 다이노스",
      "team_code": "NC",
      "innings_pitched": "3.2",
      "pitch_count": 92,
      "is_starter": true,
      "win": 0,
      "loss": 1,
      "save": 0,
      "hold": 0,
      "game_id": 80055224
    },
    {
      "player_id": "51948",
      "name": "이용준",
      "team": "NC 다이노스",
      "team_code": "NC",
      "innings_pitched": "1.1",
      "pitch_count": 41,
      "is_starter": false,
      "win": 0,
      "loss": 0,
      "save": 0,
      "hold": 0,
      "game_id": 80055224
    },
    {
      "player_id": "60339",
      "name": "김건태",
      "team": "NC 다이노스",
      "team_code": "NC",
      "innings_pitched": "2",
      "pitch_count": 47,
      "is_starter": false,
      "win": 0,
      "loss": 0,
      "save": 0,
      "hold": 0,
      "game_id": 80055224
    },
    {
      "player_id": "68639",
      "name": "하준영",
      "team": "NC 다이노스",
      "team_code": "NC",
      "innings_pitched": "1",
      "pitch_count": 17,
      "is_starter": false,
      "win": 0,
      "loss": 0,
      "save": 0,
      "hold": 0,
      "game_id": 80055224
    },
    {
      "player_id": "52994",
      "name": "박동수",
      "team": "NC 다이노스",
      "team_code": "NC",
      "innings_pitched": "1",
      "pitch_count": 22,
      "is_starter": false,
      "win": 0,
      "loss": 0,
      "save": 0,
      "hold": 0,
      "game_id": 80055224
    },
    {
      "player_id": "65320",
      "name": "최원태",
      "team": "키움 히어로즈",
      "team_code": "WO",
      "innings_pitched": "6",
      "pitch_count": 101,
      "is_starter": true,
      "win": 1,
      "loss": 0,
      "save": 0,
      "hold": 0,
      "game_id": 80055224
    },
    {
      "player_id": "69328",
      "name": "박주성",
      "team": "키움 히어로즈",
      "team_code": "WO",
      "innings_pitched": "1",
      "pitch_count": 17,
      "is_starter": false,
      "win": 0,
      "loss": 0,
      "save": 0,
      "hold": 0,
      "game_id": 80055224
    },
    {
      "player_id": "66305",
      "name": "박승주",
      "team": "키움 히어로즈",
      "team_code": "WO",
      "innings_pitched": "1",
      "pitch_count": 26,
      "is_starter": false,
      "win": 0,
      "loss": 0,
      "save": 0,
      "hold": 0,
      "game_id": 80055224
    },
    {
      "player_id": "51359",
      "name": "장재영",
      "team": "키움 히어로즈",
      "team_code": "WO",
      "innings_pitched": "1",
      "pitch_count": 11,
      "is_starter": false,
      "win": 0,
      "loss": 0,
      "save": 0,
      "hold": 0,
      "game_id": 80055224
    }
  ]
}